poker_isomorphisms/__init__.py
poker_isomorphisms/main.py
poker_isomorphisms-0.5.dist-info/METADATA
poker_isomorphisms-0.5.dist-info/WHEEL
poker_isomorphisms-0.5.dist-info/top_level.txt
poker_isomorphisms-0.5.dist-info/RECORD
