Metadata-Version: 2.1
Name: poker-isomorphisms
Version: 0.5
